lue/__init__.py
lue/__main__.py
lue/audio.py
lue/config.py
lue/content_parser.py
lue/guide.txt
lue/input_handler.py
lue/keys_default.json
lue/keys_vim.json
lue/progress_manager.py
lue/py.typed
lue/reader.py
lue/timing_calculator.py
lue/tts_manager.py
lue/ui.py
lue/tts/__init__.py
lue/tts/base.py
lue/tts/edge_tts.py
lue/tts/kokoro_tts.py
lue_reader-0.4.0.dist-info/licenses/LICENSE
lue_reader-0.4.0.dist-info/METADATA
lue_reader-0.4.0.dist-info/WHEEL
lue_reader-0.4.0.dist-info/entry_points.txt
lue_reader-0.4.0.dist-info/top_level.txt
lue_reader-0.4.0.dist-info/RECORD
