Metadata-Version: 2.4
Name: lue-reader
Version: 0.4.0
Summary: A terminal-based eBook reader with modular text-to-speech capabilities and multi-format support
Author: Starry Eyes
License: GPL-3.0-or-later
Project-URL: Homepage, https://github.com/superstarryeyes/lue
Project-URL: Repository, https://github.com/superstarryeyes/lue
Project-URL: Issues, https://github.com/superstarryeyes/lue/issues
Classifier: Development Status :: 4 - Beta
Classifier: Intended Audience :: End Users/Desktop
Classifier: License :: OSI Approved :: GNU General Public License v3 or later (GPLv3+)
Classifier: Operating System :: OS Independent
Classifier: Programming Language :: Python :: 3
Classifier: Programming Language :: Python :: 3.10
Classifier: Programming Language :: Python :: 3.11
Classifier: Programming Language :: Python :: 3.12
Classifier: Topic :: Multimedia :: Sound/Audio :: Speech
Classifier: Topic :: Text Processing
Classifier: Environment :: Console
Requires-Python: >=3.10
License-File: LICENSE
Requires-Dist: python-docx>=1.2.0
Requires-Dist: striprtf>=0.0.29
Requires-Dist: rich>=14.1.0
Requires-Dist: PyMuPDF>=1.26.3
Requires-Dist: Markdown>=3.8.2
Requires-Dist: platformdirs>=4.3.8
Requires-Dist: edge-tts>=7.2.0
Provides-Extra: kokoro
Requires-Dist: kokoro>=0.9.4; extra == "kokoro"
Requires-Dist: soundfile>=0.13.1; extra == "kokoro"
Requires-Dist: huggingface-hub>=0.34.4; extra == "kokoro"
Dynamic: license-file
